Library/__init__.py
Library/main.py
Library/utils.py
tests/__init__.py
tests/test_main.py
GaonOCR-0.1.dist-info/LICENSE
GaonOCR-0.1.dist-info/METADATA
GaonOCR-0.1.dist-info/WHEEL
GaonOCR-0.1.dist-info/top_level.txt
GaonOCR-0.1.dist-info/RECORD
